README.md
setup.cfg
setup.py
eventcore/__init__.py
eventcore/consumer.py
eventcore/decorators.py
eventcore/event.py
eventcore/exceptions.py
eventcore/producer.py
eventcore/registry.py
eventcore.egg-info/PKG-INFO
eventcore.egg-info/SOURCES.txt
eventcore.egg-info/dependency_links.txt
eventcore.egg-info/not-zip-safe
eventcore.egg-info/top_level.txt