Metadata-Version: 1.0
Name: eventcore
Version: 0.3.3
Summary: Produce and consume events with any queue.
Home-page: https://github.com/maikelboogerd/eventcore
Author: Maikel van den Boogerd
Author-email: maikelboogerd@gmail.com
License: MIT
Keywords: event,queue,producer,consumer,dispatch
Platform: UNKNOWN
